LICENSE.txt
MANIFEST.in
README.md
setup.py
hapiplot/__init__.py
hapiplot/hapiplot.py
hapiplot.egg-info/PKG-INFO
hapiplot.egg-info/SOURCES.txt
hapiplot.egg-info/dependency_links.txt
hapiplot.egg-info/requires.txt
hapiplot.egg-info/top_level.txt
hapiplot/autoplot/__init__.py
hapiplot/autoplot/autoplot.py
hapiplot/autoplot/autoplot_test.py
hapiplot/autoplot/server.jy
hapiplot/gallery/__init__.py
hapiplot/gallery/gallery.py
hapiplot/gallery/gallery_test.py
hapiplot/plot/__init__.py
hapiplot/plot/datetick.py
hapiplot/plot/datetick_explorer.py
hapiplot/plot/datetick_test.py
hapiplot/plot/heatmap.py
hapiplot/plot/heatmap_test.py
hapiplot/plot/timeseries.py
hapiplot/plot/timeseries_test.py
hapiplot/plot/util.py
test/test_hapiplot.py
test/test_hapiplot_visual.py