Metadata-Version: 2.1
Name: hapiplot
Version: 0.2.1
Summary: Plot data from HAPI server
Home-page: http://pypi.python.org/pypi/hapiplot/
Author: Bob Weigel
Author-email: rweigel@gmu.edu
License: LICENSE.txt
Platform: UNKNOWN
License-File: LICENSE.txt
